arbejdstimer/__init__.py
arbejdstimer/__main__.py
arbejdstimer/api.py
arbejdstimer/arbejdstimer.py
arbejdstimer/cli.py
arbejdstimer-2025.1.14.dist-info/LICENSE
arbejdstimer-2025.1.14.dist-info/METADATA
arbejdstimer-2025.1.14.dist-info/WHEEL
arbejdstimer-2025.1.14.dist-info/entry_points.txt
arbejdstimer-2025.1.14.dist-info/top_level.txt
arbejdstimer-2025.1.14.dist-info/RECORD
