Metadata-Version: 2.2
Name: arbejdstimer
Version: 2025.1.14
Summary: Working hours (Danish arbejdstimer) or not?
Author-email: Stefan Hagen <stefan@hagen.link>
Maintainer-email: Stefan Hagen <stefan@hagen.link>
License: MIT License
Project-URL: Homepage, https://git.sr.ht/~sthagen/arbejdstimer
Project-URL: Bug-Tracker, https://todo.sr.ht/~sthagen/arbejdstimer
Project-URL: Documentation, https://codes.dilettant.life/docs/arbejdstimer
Project-URL: Source-Code, https://git.sr.ht/~sthagen/arbejdstimer
Project-URL: Test-Coverage, https://codes.dilettant.life/coverage/arbejdstimer
Keywords: developer-tools,documentation-tools,html,markdown
Classifier: Development Status :: 3 - Alpha
Classifier: Intended Audience :: Developers
Classifier: License :: OSI Approved :: MIT License
Classifier: Programming Language :: Python :: 3.10
Classifier: Programming Language :: Python :: 3.11
Classifier: Programming Language :: Python :: 3.12
Classifier: Programming Language :: Python :: 3.13
Classifier: Programming Language :: Python :: 3.9
Requires-Python: >=3.9
License-File: LICENSE
Requires-Dist: pydantic>=2.10.5
Requires-Dist: typer>=0.15.1
Provides-Extra: dev
Requires-Dist: black; extra == "dev"
Requires-Dist: coverage; extra == "dev"
Requires-Dist: hypothesis; extra == "dev"
Requires-Dist: mypy; extra == "dev"
Requires-Dist: pytest; extra == "dev"
Requires-Dist: pytest-cov; extra == "dev"
Requires-Dist: pytest-flake8; extra == "dev"
Requires-Dist: ruff; extra == "dev"
